README.md
setup.cfg
setup.py
WuttaPOS.egg-info/PKG-INFO
WuttaPOS.egg-info/SOURCES.txt
WuttaPOS.egg-info/dependency_links.txt
WuttaPOS.egg-info/entry_points.txt
WuttaPOS.egg-info/requires.txt
WuttaPOS.egg-info/top_level.txt
wuttapos/__init__.py
wuttapos/_version.py
wuttapos/app.py
wuttapos/commands.py
wuttapos/controls/__init__.py
wuttapos/controls/base.py
wuttapos/controls/header.py
wuttapos/controls/timestamp.py
wuttapos/views/__init__.py
wuttapos/views/base.py
wuttapos/views/login.py
wuttapos/views/pos.py